ab_core/auth_flow/__init__.py
ab_core/auth_flow/oauth2/flow/__init__.py
ab_core/auth_flow/oauth2/flow/base.py
ab_core/auth_flow/oauth2/flow/impersonation.py
ab_core/auth_flow/oauth2/flow/template.py
ab_core/auth_flow/oauth2/schema/__init__.py
ab_core/auth_flow/oauth2/schema/auth_code_stage.py
ab_core/auth_flow/oauth2/schema/flow_type.py
ab_auth_flow-0.2.5.dist-info/METADATA
ab_auth_flow-0.2.5.dist-info/WHEEL
ab_auth_flow-0.2.5.dist-info/licenses/LICENSE
ab_auth_flow-0.2.5.dist-info/RECORD
