Metadata-Version: 2.4
Name: ab-auth-flow
Version: 0.2.5
Author-email: Matthew Coulter <53892067+mattcoulter7@users.noreply.github.com>
License-File: LICENSE
Requires-Python: <4,>=3.12
Requires-Dist: ab-auth-client<0.2.0,>=0.1.7
Requires-Dist: ab-impersonation<0.3.0,>=0.2.0
Requires-Dist: pydantic<3,>=2.11.7
